AnIntroductionToDataScience/README.md
AnIntroductionToDataScience/__init__.py
AnIntroductionToDataScience/__main__.py
AnIntroductionToDataScience/file.epub
AnIntroductionToDataScience/index.html
AnIntroductionToDataScience/css/__init__.py
AnIntroductionToDataScience/css/annotations.css
AnIntroductionToDataScience/css/main.css
AnIntroductionToDataScience/css/normalize.css
AnIntroductionToDataScience/css/popup.css
AnIntroductionToDataScience/font/__init__.py
AnIntroductionToDataScience/font/fontello.eot
AnIntroductionToDataScience/font/fontello.svg
AnIntroductionToDataScience/font/fontello.ttf
AnIntroductionToDataScience/font/fontello.woff
AnIntroductionToDataScience/img/__init__.py
AnIntroductionToDataScience/img/annotator-glyph-sprite.png
AnIntroductionToDataScience/img/annotator-icon-sprite.png
AnIntroductionToDataScience/img/apple-touch-icon.png
AnIntroductionToDataScience/img/cancelfullscreen.png
AnIntroductionToDataScience/img/close.png
AnIntroductionToDataScience/img/fullscreen.png
AnIntroductionToDataScience/img/loader.gif
AnIntroductionToDataScience/img/menu-icon.png
AnIntroductionToDataScience/img/save.png
AnIntroductionToDataScience/img/saved.png
AnIntroductionToDataScience/img/settings-s.png
AnIntroductionToDataScience/img/settings.png
AnIntroductionToDataScience/img/star.png
AnIntroductionToDataScience/js/__init__.py
AnIntroductionToDataScience/js/epub.js
AnIntroductionToDataScience/js/epub.min.js
AnIntroductionToDataScience/js/epub.min.map
AnIntroductionToDataScience/js/hooks.min.js
AnIntroductionToDataScience/js/hooks.min.map
AnIntroductionToDataScience/js/reader.js
AnIntroductionToDataScience/js/reader.js.map
AnIntroductionToDataScience/js/reader.min.js
AnIntroductionToDataScience/js/reader.min.map
AnIntroductionToDataScience/js/hooks/__init__.py
AnIntroductionToDataScience/js/hooks/extensions/__init__.py
AnIntroductionToDataScience/js/hooks/extensions/highlight.js
AnIntroductionToDataScience/js/libs/__init__.py
an_introduction_to_data_science-2024.3.3.0.dist-info/METADATA
an_introduction_to_data_science-2024.3.3.0.dist-info/WHEEL
an_introduction_to_data_science-2024.3.3.0.dist-info/entry_points.txt
an_introduction_to_data_science-2024.3.3.0.dist-info/top_level.txt
an_introduction_to_data_science-2024.3.3.0.dist-info/RECORD
